setup.py
eggshell/__init__.py
eggshell.egg-info/PKG-INFO
eggshell.egg-info/SOURCES.txt
eggshell.egg-info/dependency_links.txt
eggshell.egg-info/top_level.txt