Metadata-Version: 1.1
Name: eggshell
Version: 1.0
Summary: Eggshell is a shell interface
Home-page: http://github.com/scottfrazer/eggshell
Author: Scott Frazer
Author-email: scott.d.frazer@gmail.com
License: MIT
Keywords: Bash,Shell
Platform: UNKNOWN
Classifier: License :: OSI Approved :: MIT License
Classifier: Programming Language :: Python
Classifier: Development Status :: 4 - Beta
Classifier: Intended Audience :: Developers
Classifier: Natural Language :: English
